convo_orchestrator/__init__.py
convo_orchestrator/adapters/__init__.py
convo_orchestrator/adapters/encoder_ollama.py
convo_orchestrator/adapters/llm_ollama.py
convo_orchestrator/adapters/memory_events.py
convo_orchestrator/adapters/postgres_lexical.py
convo_orchestrator/adapters/postgres_notify.py
convo_orchestrator/adapters/qdrant_store.py
convo_orchestrator/application/__init__.py
convo_orchestrator/application/conversation_service.py
convo_orchestrator/application/events.py
convo_orchestrator/application/llm_service.py
convo_orchestrator/application/prompt_builder.py
convo_orchestrator/application/rag_context_service.py
convo_orchestrator/application/rag_service.py
convo_orchestrator/application/selection_service.py
convo_orchestrator/application/summarization_service.py
convo_orchestrator/domain/__init__.py
convo_orchestrator/domain/chat_domain.py
convo_orchestrator/domain/events.py
convo_orchestrator/domain/llm_domain.py
convo_orchestrator/domain/prompt_domain.py
convo_orchestrator/domain/rag_domain.py
convo_orchestrator/domain/selection.py
convo_orchestrator/shared/__init__.py
convo_orchestrator/shared/config.py
convo_orchestrator/shared/error.py
convo_orchestrator/shared/logger.py
convo_orchestrator/shared/result.py
convo_orchestrator-0.1.0.dist-info/METADATA
convo_orchestrator-0.1.0.dist-info/WHEEL
convo_orchestrator-0.1.0.dist-info/RECORD
