Metadata-Version: 2.4
Name: convo-orchestrator
Version: 0.1.0
Summary: Orchestrated RAG components: Postgres lexical, Qdrant vectors, Ollama LLM/embeddings, chat services & examples.
Author-email: Julio Galindo <juliogalindo922@gmail.com>
License: MIT
Keywords: chat,ollama,postgres,qdrant,rag,sse
Classifier: Development Status :: 3 - Alpha
Classifier: Intended Audience :: Developers
Classifier: License :: OSI Approved :: MIT License
Classifier: Operating System :: OS Independent
Classifier: Programming Language :: Python :: 3
Classifier: Programming Language :: Python :: 3.12
Requires-Python: >=3.12
Requires-Dist: asyncpg>=0.30.0
Requires-Dist: psycopg[binary]>=3.2.10
Requires-Dist: python-dotenv>=1.1.1
Requires-Dist: qdrant-client>=1.15.1
